hostinger_cli/__init__.py
hostinger_cli/api_client.py
hostinger_cli/main.py
hostinger_cli/commands/__init__.py
hostinger_cli/commands/billing.py
hostinger_cli/commands/dns.py
hostinger_cli/commands/domains.py
hostinger_cli/commands/vps.py
hostinger_cli/utils/__init__.py
hostinger_cli/utils/config.py
hostinger_cli/utils/formatters.py
hostinger_cli-1.0.0.dist-info/licenses/LICENSE
hostinger_cli-1.0.0.dist-info/METADATA
hostinger_cli-1.0.0.dist-info/WHEEL
hostinger_cli-1.0.0.dist-info/entry_points.txt
hostinger_cli-1.0.0.dist-info/top_level.txt
hostinger_cli-1.0.0.dist-info/RECORD
