Metadata-Version: 2.4
Name: hostinger-cli
Version: 1.0.0
Summary: A comprehensive command-line interface for Hostinger API
Home-page: https://github.com/hostinger/hostinger-cli
Author: Hostinger CLI Contributors
Author-email: Hostinger CLI Contributors <support@hostinger.com>
Maintainer-email: Hostinger CLI Contributors <support@hostinger.com>
License: MIT
Project-URL: Homepage, https://github.com/hostinger/hostinger-cli
Project-URL: Documentation, https://developers.hostinger.com
Project-URL: Repository, https://github.com/hostinger/hostinger-cli
Project-URL: Bug Reports, https://github.com/hostinger/hostinger-cli/issues
Project-URL: Changelog, https://github.com/hostinger/hostinger-cli/blob/main/CHANGELOG.md
Keywords: hostinger,api,cli,cloud,vps,domains,dns,hosting,web hosting,server management,domain management
Classifier: Development Status :: 4 - Beta
Classifier: Intended Audience :: Developers
Classifier: Intended Audience :: System Administrators
Classifier: License :: OSI Approved :: MIT License
Classifier: Operating System :: OS Independent
Classifier: Programming Language :: Python :: 3
Classifier: Programming Language :: Python :: 3.8
Classifier: Programming Language :: Python :: 3.9
Classifier: Programming Language :: Python :: 3.10
Classifier: Programming Language :: Python :: 3.11
Classifier: Programming Language :: Python :: 3.12
Classifier: Topic :: Internet :: WWW/HTTP
Classifier: Topic :: System :: Systems Administration
Classifier: Topic :: Software Development :: Libraries :: Python Modules
Classifier: Topic :: Utilities
Requires-Python: >=3.8
License-File: LICENSE
Requires-Dist: click>=8.0.0
Requires-Dist: requests>=2.25.0
Provides-Extra: dev
Requires-Dist: pytest>=6.0; extra == "dev"
Requires-Dist: pytest-cov>=2.0; extra == "dev"
Requires-Dist: black>=22.0; extra == "dev"
Requires-Dist: flake8>=4.0; extra == "dev"
Requires-Dist: mypy>=0.950; extra == "dev"
Requires-Dist: pre-commit>=2.15.0; extra == "dev"
Dynamic: author
Dynamic: home-page
Dynamic: license-file
Dynamic: requires-python
